mysql_enc_ini/__init__.py
mysql_enc_ini/mysql_enc_ini.py
mysql_enc_ini-0.6.5.dist-info/LICENSE
mysql_enc_ini-0.6.5.dist-info/METADATA
mysql_enc_ini-0.6.5.dist-info/WHEEL
mysql_enc_ini-0.6.5.dist-info/top_level.txt
mysql_enc_ini-0.6.5.dist-info/RECORD
