Metadata-Version: 2.1
Name: mysql-enc-ini
Version: 0.6.5
Summary: Encrypt MySQL connection information
Author-email: Joel Sabouret <joel@netwitch.de>
Project-URL: Homepage, https://github.com/jsabouret/mysql_enc_ini
Project-URL: Bug Tracker, https://github.com/jsabouret/mysql_enc_ini/issues
Classifier: License :: OSI Approved :: GNU General Public License v3 or later (GPLv3+)
Classifier: Programming Language :: Python :: 3
Classifier: Operating System :: OS Independent
Requires-Python: >=3.6
License-File: LICENSE
Requires-Dist: cryptography (>=37.0)
Requires-Dist: configparser (>=5.2)
